htmlExtractor/__init__.py
htmlExtractor/main.py
htmlExtractor-0.0.1.dist-info/METADATA
htmlExtractor-0.0.1.dist-info/WHEEL
htmlExtractor-0.0.1.dist-info/top_level.txt
htmlExtractor-0.0.1.dist-info/RECORD
