Metadata-Version: 2.1
Name: htmlExtractor
Version: 0.0.1
Summary: A simple package to fetch HTML data from a website
Home-page: https://github.com/AnisurRahman06046/fetchHtml_website.git
Author: Md Anisur Rahman
Author-email: anisurrahman06046@gmail.com
Classifier: Programming Language :: Python :: 3
Classifier: License :: OSI Approved :: MIT License
Classifier: Operating System :: OS Independent
Requires-Python: >=3.6
Requires-Dist: requests
Requires-Dist: beautifulsoup4
